{
    "package": "Bike Bicycle",
    "imgList": [
        {
            "src": "https://cdn-icons-png.flaticon.com/256/8466/8466028.png",
            "alt": "Bike"
        },
        {
            "src": "https://cdn-icons-png.flaticon.com/256/8466/8466029.png",
            "alt": "Bike"
        },
        {
            "src": "https://cdn-icons-png.flaticon.com/256/8466/8466030.png",
            "alt": "Bike"
        },
        {
            "src": "https://cdn-icons-png.flaticon.com/256/8466/8466031.png",
            "alt": "Bike"
        },
        {
            "src": "https://cdn-icons-png.flaticon.com/256/8466/8466032.png",
            "alt": "Bike"
        },
        {
            "src": "https://cdn-icons-png.flaticon.com/256/8466/8466033.png",
            "alt": "Bike"
        },
        {
            "src": "https://cdn-icons-png.flaticon.com/256/8466/8466034.png",
            "alt": "Bike"
        },
        {
            "src": "https://cdn-icons-png.flaticon.com/256/8466/8466035.png",
            "alt": "Bike"
        },
        {
            "src": "https://cdn-icons-png.flaticon.com/256/8466/8466036.png",
            "alt": "Bike"
        },
        {
            "src": "https://cdn-icons-png.flaticon.com/256/8466/8466039.png",
            "alt": "Bike"
        },
        {
            "src": "https://cdn-icons-png.flaticon.com/256/8466/8466041.png",
            "alt": "Bike"
        },
        {
            "src": "https://cdn-icons-png.flaticon.com/256/8466/8466045.png",
            "alt": "Bike"
        },
        {
            "src": "https://cdn-icons-png.flaticon.com/256/8466/8466048.png",
            "alt": "Bike"
        },
        {
            "src": "https://cdn-icons-png.flaticon.com/256/8466/8466051.png",
            "alt": "Bike"
        },
        {
            "src": "https://cdn-icons-png.flaticon.com/256/8466/8466054.png",
            "alt": "Bike"
        },
        {
            "src": "https://cdn-icons-png.flaticon.com/256/8466/8466057.png",
            "alt": "Bike"
        },
        {
            "src": "https://cdn-icons-png.flaticon.com/256/8466/8466060.png",
            "alt": "Bike"
        },
        {
            "src": "https://cdn-icons-png.flaticon.com/256/8466/8466063.png",
            "alt": "Bike"
        },
        {
            "src": "https://cdn-icons-png.flaticon.com/256/8466/8466066.png",
            "alt": "Bike"
        },
        {
            "src": "https://cdn-icons-png.flaticon.com/256/8466/8466069.png",
            "alt": "Bike"
        },
        {
            "src": "https://cdn-icons-png.flaticon.com/256/8564/8564573.png",
            "alt": "Bike "
        },
        {
            "src": "https://cdn-icons-png.flaticon.com/256/8564/8564575.png",
            "alt": "Bike "
        },
        {
            "src": "https://cdn-icons-png.flaticon.com/256/8564/8564577.png",
            "alt": "Bike "
        },
        {
            "src": "https://cdn-icons-png.flaticon.com/256/8564/8564579.png",
            "alt": "Bike "
        },
        {
            "src": "https://cdn-icons-png.flaticon.com/256/8564/8564581.png",
            "alt": "Bike "
        },
        {
            "src": "https://cdn-icons-png.flaticon.com/256/8564/8564583.png",
            "alt": "Bike "
        },
        {
            "src": "https://cdn-icons-png.flaticon.com/256/8564/8564585.png",
            "alt": "Bike "
        },
        {
            "src": "https://cdn-icons-png.flaticon.com/256/8564/8564587.png",
            "alt": "Bike "
        },
        {
            "src": "https://cdn-icons-png.flaticon.com/256/8564/8564588.png",
            "alt": "Bike "
        },
        {
            "src": "https://cdn-icons-png.flaticon.com/256/8564/8564590.png",
            "alt": "Bike "
        },
        {
            "src": "https://cdn-icons-png.flaticon.com/256/8564/8564592.png",
            "alt": "Bike "
        },
        {
            "src": "https://cdn-icons-png.flaticon.com/256/8564/8564594.png",
            "alt": "Bike "
        },
        {
            "src": "https://cdn-icons-png.flaticon.com/256/8564/8564596.png",
            "alt": "Bike "
        },
        {
            "src": "https://cdn-icons-png.flaticon.com/256/8564/8564598.png",
            "alt": "Bike "
        },
        {
            "src": "https://cdn-icons-png.flaticon.com/256/8564/8564600.png",
            "alt": "Bike "
        },
        {
            "src": "https://cdn-icons-png.flaticon.com/256/8564/8564601.png",
            "alt": "Bike "
        },
        {
            "src": "https://cdn-icons-png.flaticon.com/256/8564/8564605.png",
            "alt": "Bike "
        },
        {
            "src": "https://cdn-icons-png.flaticon.com/256/8564/8564610.png",
            "alt": "Bike "
        },
        {
            "src": "https://cdn-icons-png.flaticon.com/256/8564/8564616.png",
            "alt": "Bike "
        },
        {
            "src": "https://cdn-icons-png.flaticon.com/256/8564/8564621.png",
            "alt": "Bike "
        }
    ]
}