{
    "package": "Camping Adventure",
    "imgList": [
        {
            "src": "https://cdn-icons-png.flaticon.com/256/8703/8703550.png",
            "alt": "axe"
        },
        {
            "src": "https://cdn-icons-png.flaticon.com/256/8703/8703553.png",
            "alt": "Backpack"
        },
        {
            "src": "https://cdn-icons-png.flaticon.com/256/8703/8703556.png",
            "alt": "BBQ grill"
        },
        {
            "src": "https://cdn-icons-png.flaticon.com/256/8703/8703559.png",
            "alt": "Binocular"
        },
        {
            "src": "https://cdn-icons-png.flaticon.com/256/8703/8703562.png",
            "alt": "Campfire"
        },
        {
            "src": "https://cdn-icons-png.flaticon.com/256/8703/8703565.png",
            "alt": "Canned food"
        },
        {
            "src": "https://cdn-icons-png.flaticon.com/256/8703/8703568.png",
            "alt": "Canoe"
        },
        {
            "src": "https://cdn-icons-png.flaticon.com/256/8703/8703572.png",
            "alt": "Compass"
        },
        {
            "src": "https://cdn-icons-png.flaticon.com/256/8703/8703575.png",
            "alt": "Cottage"
        },
        {
            "src": "https://cdn-icons-png.flaticon.com/256/8703/8703577.png",
            "alt": "Tourist"
        },
        {
            "src": "https://cdn-icons-png.flaticon.com/256/8703/8703579.png",
            "alt": "First aid"
        },
        {
            "src": "https://cdn-icons-png.flaticon.com/256/8703/8703581.png",
            "alt": "Flashlight"
        },
        {
            "src": "https://cdn-icons-png.flaticon.com/256/8703/8703583.png",
            "alt": "Gas stove"
        },
        {
            "src": "https://cdn-icons-png.flaticon.com/256/8703/8703585.png",
            "alt": "Shoes"
        },
        {
            "src": "https://cdn-icons-png.flaticon.com/256/8703/8703587.png",
            "alt": "Lamp"
        },
        {
            "src": "https://cdn-icons-png.flaticon.com/256/8703/8703589.png",
            "alt": "Lighter"
        },
        {
            "src": "https://cdn-icons-png.flaticon.com/256/8703/8703591.png",
            "alt": "Male"
        },
        {
            "src": "https://cdn-icons-png.flaticon.com/256/8703/8703593.png",
            "alt": "Map"
        },
        {
            "src": "https://cdn-icons-png.flaticon.com/256/8703/8703595.png",
            "alt": "Pocket"
        },
        {
            "src": "https://cdn-icons-png.flaticon.com/256/8703/8703596.png",
            "alt": "Radio"
        },
        {
            "src": "https://cdn-icons-png.flaticon.com/256/8703/8703597.png",
            "alt": "Rope"
        },
        {
            "src": "https://cdn-icons-png.flaticon.com/256/8703/8703598.png",
            "alt": "Teapot"
        },
        {
            "src": "https://cdn-icons-png.flaticon.com/256/8703/8703599.png",
            "alt": "Tent"
        },
        {
            "src": "https://cdn-icons-png.flaticon.com/256/8703/8703600.png",
            "alt": "Tumbler"
        },
        {
            "src": "https://cdn-icons-png.flaticon.com/256/8703/8703603.png",
            "alt": "Walkie talkie"
        }
    ]
}