{
    "package": "Dragonfly",
    "imgList": [
        {
            "src": "https://cdn-icons-png.flaticon.com/256/8360/8360108.png",
            "alt": "Dragonfly"
        },
        {
            "src": "https://cdn-icons-png.flaticon.com/256/8360/8360111.png",
            "alt": "Dragonfly"
        },
        {
            "src": "https://cdn-icons-png.flaticon.com/256/8360/8360114.png",
            "alt": "Dragonfly"
        },
        {
            "src": "https://cdn-icons-png.flaticon.com/256/8360/8360119.png",
            "alt": "Dragonfly"
        },
        {
            "src": "https://cdn-icons-png.flaticon.com/256/8360/8360123.png",
            "alt": "Dragonfly"
        },
        {
            "src": "https://cdn-icons-png.flaticon.com/256/8360/8360127.png",
            "alt": "Dragonfly"
        },
        {
            "src": "https://cdn-icons-png.flaticon.com/256/8360/8360130.png",
            "alt": "Dragonfly"
        },
        {
            "src": "https://cdn-icons-png.flaticon.com/256/8360/8360134.png",
            "alt": "Dragonfly"
        },
        {
            "src": "https://cdn-icons-png.flaticon.com/256/8360/8360138.png",
            "alt": "Dragonfly"
        },
        {
            "src": "https://cdn-icons-png.flaticon.com/256/8360/8360142.png",
            "alt": "Dragonfly"
        },
        {
            "src": "https://cdn-icons-png.flaticon.com/256/8360/8360146.png",
            "alt": "Dragonfly"
        },
        {
            "src": "https://cdn-icons-png.flaticon.com/256/8360/8360150.png",
            "alt": "Dragonfly"
        },
        {
            "src": "https://cdn-icons-png.flaticon.com/256/8360/8360154.png",
            "alt": "Dragonfly"
        },
        {
            "src": "https://cdn-icons-png.flaticon.com/256/8360/8360158.png",
            "alt": "Dragonfly"
        },
        {
            "src": "https://cdn-icons-png.flaticon.com/256/8360/8360162.png",
            "alt": "Dragonfly"
        },
        {
            "src": "https://cdn-icons-png.flaticon.com/256/8360/8360166.png",
            "alt": "Dragonfly"
        },
        {
            "src": "https://cdn-icons-png.flaticon.com/256/8360/8360170.png",
            "alt": "Dragonfly"
        },
        {
            "src": "https://cdn-icons-png.flaticon.com/256/8360/8360174.png",
            "alt": "Dragonfly"
        },
        {
            "src": "https://cdn-icons-png.flaticon.com/256/8360/8360179.png",
            "alt": "Dragonfly"
        },
        {
            "src": "https://cdn-icons-png.flaticon.com/256/8360/8360182.png",
            "alt": "Dragonfly"
        }
    ]
}