{
    "package": "Family Car",
    "imgList": [
        {
            "src": "https://cdn-icons-png.flaticon.com/256/6907/6907358.png",
            "alt": "Family car"
        },
        {
            "src": "https://cdn-icons-png.flaticon.com/256/6907/6907363.png",
            "alt": "Family car"
        },
        {
            "src": "https://cdn-icons-png.flaticon.com/256/6907/6907368.png",
            "alt": "Family car"
        },
        {
            "src": "https://cdn-icons-png.flaticon.com/256/6907/6907373.png",
            "alt": "Family car"
        },
        {
            "src": "https://cdn-icons-png.flaticon.com/256/6907/6907378.png",
            "alt": "Family car"
        },
        {
            "src": "https://cdn-icons-png.flaticon.com/256/6907/6907383.png",
            "alt": "Family car"
        },
        {
            "src": "https://cdn-icons-png.flaticon.com/256/6907/6907388.png",
            "alt": "Family car"
        },
        {
            "src": "https://cdn-icons-png.flaticon.com/256/6907/6907393.png",
            "alt": "Family car"
        },
        {
            "src": "https://cdn-icons-png.flaticon.com/256/6907/6907398.png",
            "alt": "Family car"
        },
        {
            "src": "https://cdn-icons-png.flaticon.com/256/6907/6907403.png",
            "alt": "Family car"
        },
        {
            "src": "https://cdn-icons-png.flaticon.com/256/6907/6907407.png",
            "alt": "Family car"
        },
        {
            "src": "https://cdn-icons-png.flaticon.com/256/6907/6907412.png",
            "alt": "Family car"
        },
        {
            "src": "https://cdn-icons-png.flaticon.com/256/6907/6907416.png",
            "alt": "Family car"
        },
        {
            "src": "https://cdn-icons-png.flaticon.com/256/6907/6907420.png",
            "alt": "Family car"
        },
        {
            "src": "https://cdn-icons-png.flaticon.com/256/6907/6907424.png",
            "alt": "Family car"
        },
        {
            "src": "https://cdn-icons-png.flaticon.com/256/6907/6907428.png",
            "alt": "Family car"
        },
        {
            "src": "https://cdn-icons-png.flaticon.com/256/6907/6907432.png",
            "alt": "Family car"
        },
        {
            "src": "https://cdn-icons-png.flaticon.com/256/6907/6907436.png",
            "alt": "Family car"
        },
        {
            "src": "https://cdn-icons-png.flaticon.com/256/6907/6907440.png",
            "alt": "Family car"
        },
        {
            "src": "https://cdn-icons-png.flaticon.com/256/6907/6907444.png",
            "alt": "Family car"
        }
    ]
}