{
    "package": "Funny cat stickers",
    "imgList": [
        {
            "src": "https://cdn-icons-png.flaticon.com/256/5722/5722288.png",
            "alt": "Cat animal"
        },
        {
            "src": "https://cdn-icons-png.flaticon.com/256/5722/5722295.png",
            "alt": "Cat animal"
        },
        {
            "src": "https://cdn-icons-png.flaticon.com/256/5722/5722301.png",
            "alt": "Cat animal"
        },
        {
            "src": "https://cdn-icons-png.flaticon.com/256/5722/5722306.png",
            "alt": "Cat animal"
        },
        {
            "src": "https://cdn-icons-png.flaticon.com/256/5722/5722312.png",
            "alt": "Cat animal"
        },
        {
            "src": "https://cdn-icons-png.flaticon.com/256/5722/5722317.png",
            "alt": "Cat animal"
        },
        {
            "src": "https://cdn-icons-png.flaticon.com/256/5722/5722323.png",
            "alt": "Cat animal"
        },
        {
            "src": "https://cdn-icons-png.flaticon.com/256/5722/5722328.png",
            "alt": "Cat animal"
        },
        {
            "src": "https://cdn-icons-png.flaticon.com/256/5722/5722333.png",
            "alt": "Cat animal"
        },
        {
            "src": "https://cdn-icons-png.flaticon.com/256/5722/5722338.png",
            "alt": "Cat animal"
        },
        {
            "src": "https://cdn-icons-png.flaticon.com/256/5722/5722341.png",
            "alt": "Cat animal"
        },
        {
            "src": "https://cdn-icons-png.flaticon.com/256/5722/5722354.png",
            "alt": "Cat animal"
        },
        {
            "src": "https://cdn-icons-png.flaticon.com/256/5722/5722362.png",
            "alt": "Cat animal"
        },
        {
            "src": "https://cdn-icons-png.flaticon.com/256/5722/5722370.png",
            "alt": "Cat animal"
        },
        {
            "src": "https://cdn-icons-png.flaticon.com/256/5722/5722379.png",
            "alt": "Cat animal"
        },
        {
            "src": "https://cdn-icons-png.flaticon.com/256/5722/5722384.png",
            "alt": "Cat animal"
        },
        {
            "src": "https://cdn-icons-png.flaticon.com/256/5722/5722392.png",
            "alt": "Cat animal"
        },
        {
            "src": "https://cdn-icons-png.flaticon.com/256/5722/5722400.png",
            "alt": "Cat animal"
        },
        {
            "src": "https://cdn-icons-png.flaticon.com/256/5722/5722408.png",
            "alt": "Cat animal"
        },
        {
            "src": "https://cdn-icons-png.flaticon.com/256/5722/5722416.png",
            "alt": "Cat animal"
        }
    ]
}