{
    "package": "Gifts",
    "imgList": [
        {
            "src": "https://cdn-icons-png.flaticon.com/256/12535/12535784.png",
            "alt": "Gift"
        },
        {
            "src": "https://cdn-icons-png.flaticon.com/256/12535/12535785.png",
            "alt": "Gift"
        },
        {
            "src": "https://cdn-icons-png.flaticon.com/256/12535/12535786.png",
            "alt": "Gift"
        },
        {
            "src": "https://cdn-icons-png.flaticon.com/256/12535/12535787.png",
            "alt": "Gift"
        },
        {
            "src": "https://cdn-icons-png.flaticon.com/256/12535/12535788.png",
            "alt": "Gift"
        },
        {
            "src": "https://cdn-icons-png.flaticon.com/256/12535/12535789.png",
            "alt": "Gift"
        },
        {
            "src": "https://cdn-icons-png.flaticon.com/256/12535/12535790.png",
            "alt": "Gift"
        },
        {
            "src": "https://cdn-icons-png.flaticon.com/256/12535/12535791.png",
            "alt": "Gift"
        },
        {
            "src": "https://cdn-icons-png.flaticon.com/256/12535/12535792.png",
            "alt": "Gift"
        },
        {
            "src": "https://cdn-icons-png.flaticon.com/256/12535/12535793.png",
            "alt": "Gift"
        },
        {
            "src": "https://cdn-icons-png.flaticon.com/256/12535/12535794.png",
            "alt": "Gift"
        },
        {
            "src": "https://cdn-icons-png.flaticon.com/256/12535/12535795.png",
            "alt": "Gift"
        },
        {
            "src": "https://cdn-icons-png.flaticon.com/256/12535/12535796.png",
            "alt": "Gift"
        },
        {
            "src": "https://cdn-icons-png.flaticon.com/256/12535/12535797.png",
            "alt": "Gift"
        },
        {
            "src": "https://cdn-icons-png.flaticon.com/256/12535/12535798.png",
            "alt": "Gift"
        },
        {
            "src": "https://cdn-icons-png.flaticon.com/256/12535/12535799.png",
            "alt": "Gift"
        },
        {
            "src": "https://cdn-icons-png.flaticon.com/256/12535/12535800.png",
            "alt": "Gift"
        },
        {
            "src": "https://cdn-icons-png.flaticon.com/256/12535/12535801.png",
            "alt": "Gift"
        },
        {
            "src": "https://cdn-icons-png.flaticon.com/256/12535/12535802.png",
            "alt": "Gift"
        },
        {
            "src": "https://cdn-icons-png.flaticon.com/256/12535/12535803.png",
            "alt": "Gift"
        },
        {
            "src": "https://cdn-icons-png.flaticon.com/256/12690/12690645.png",
            "alt": "Gift"
        },
        {
            "src": "https://cdn-icons-png.flaticon.com/256/12690/12690646.png",
            "alt": "Gift"
        },
        {
            "src": "https://cdn-icons-png.flaticon.com/256/12690/12690647.png",
            "alt": "Gift"
        },
        {
            "src": "https://cdn-icons-png.flaticon.com/256/12690/12690648.png",
            "alt": "Gift"
        },
        {
            "src": "https://cdn-icons-png.flaticon.com/256/12690/12690649.png",
            "alt": "Gift"
        },
        {
            "src": "https://cdn-icons-png.flaticon.com/256/12690/12690650.png",
            "alt": "Gift"
        },
        {
            "src": "https://cdn-icons-png.flaticon.com/256/12690/12690651.png",
            "alt": "Gift"
        },
        {
            "src": "https://cdn-icons-png.flaticon.com/256/12690/12690652.png",
            "alt": "Gift"
        },
        {
            "src": "https://cdn-icons-png.flaticon.com/256/12690/12690653.png",
            "alt": "Gift"
        },
        {
            "src": "https://cdn-icons-png.flaticon.com/256/12690/12690654.png",
            "alt": "Gift"
        },
        {
            "src": "https://cdn-icons-png.flaticon.com/256/12690/12690655.png",
            "alt": "Gift"
        },
        {
            "src": "https://cdn-icons-png.flaticon.com/256/12690/12690656.png",
            "alt": "Gift"
        },
        {
            "src": "https://cdn-icons-png.flaticon.com/256/12690/12690657.png",
            "alt": "Gift"
        },
        {
            "src": "https://cdn-icons-png.flaticon.com/256/12690/12690658.png",
            "alt": "Gift"
        },
        {
            "src": "https://cdn-icons-png.flaticon.com/256/12690/12690659.png",
            "alt": "Gift"
        },
        {
            "src": "https://cdn-icons-png.flaticon.com/256/12690/12690660.png",
            "alt": "Gift"
        },
        {
            "src": "https://cdn-icons-png.flaticon.com/256/12690/12690661.png",
            "alt": "Gift"
        },
        {
            "src": "https://cdn-icons-png.flaticon.com/256/12690/12690662.png",
            "alt": "Gift"
        },
        {
            "src": "https://cdn-icons-png.flaticon.com/256/12690/12690663.png",
            "alt": "Gift"
        },
        {
            "src": "https://cdn-icons-png.flaticon.com/256/12690/12690664.png",
            "alt": "Gift"
        },
        {
            "src": "https://cdn-icons-png.flaticon.com/256/12691/12691134.png",
            "alt": "Gift"
        },
        {
            "src": "https://cdn-icons-png.flaticon.com/256/12691/12691135.png",
            "alt": "Gift"
        },
        {
            "src": "https://cdn-icons-png.flaticon.com/256/12691/12691136.png",
            "alt": "Gift"
        },
        {
            "src": "https://cdn-icons-png.flaticon.com/256/12691/12691137.png",
            "alt": "Gift"
        },
        {
            "src": "https://cdn-icons-png.flaticon.com/256/12691/12691138.png",
            "alt": "Gift"
        },
        {
            "src": "https://cdn-icons-png.flaticon.com/256/12691/12691139.png",
            "alt": "Gift"
        },
        {
            "src": "https://cdn-icons-png.flaticon.com/256/12691/12691140.png",
            "alt": "Gift"
        },
        {
            "src": "https://cdn-icons-png.flaticon.com/256/12691/12691141.png",
            "alt": "Gift"
        },
        {
            "src": "https://cdn-icons-png.flaticon.com/256/12691/12691142.png",
            "alt": "Gift"
        },
        {
            "src": "https://cdn-icons-png.flaticon.com/256/12691/12691143.png",
            "alt": "Gift"
        },
        {
            "src": "https://cdn-icons-png.flaticon.com/256/12691/12691144.png",
            "alt": "Gift"
        },
        {
            "src": "https://cdn-icons-png.flaticon.com/256/12691/12691145.png",
            "alt": "Gift"
        },
        {
            "src": "https://cdn-icons-png.flaticon.com/256/12691/12691146.png",
            "alt": "Gift"
        },
        {
            "src": "https://cdn-icons-png.flaticon.com/256/12691/12691147.png",
            "alt": "Gift"
        },
        {
            "src": "https://cdn-icons-png.flaticon.com/256/12691/12691148.png",
            "alt": "Gift"
        },
        {
            "src": "https://cdn-icons-png.flaticon.com/256/12691/12691149.png",
            "alt": "Gift"
        },
        {
            "src": "https://cdn-icons-png.flaticon.com/256/12691/12691150.png",
            "alt": "Gift"
        },
        {
            "src": "https://cdn-icons-png.flaticon.com/256/12691/12691151.png",
            "alt": "Gift"
        },
        {
            "src": "https://cdn-icons-png.flaticon.com/256/12691/12691152.png",
            "alt": "Gift"
        },
        {
            "src": "https://cdn-icons-png.flaticon.com/256/12691/12691153.png",
            "alt": "Gift"
        },
        {
            "src": "https://cdn-icons-png.flaticon.com/256/12792/12792033.png",
            "alt": "Gift"
        },
        {
            "src": "https://cdn-icons-png.flaticon.com/256/12792/12792037.png",
            "alt": "Gift"
        },
        {
            "src": "https://cdn-icons-png.flaticon.com/256/12792/12792041.png",
            "alt": "Gift"
        },
        {
            "src": "https://cdn-icons-png.flaticon.com/256/12792/12792045.png",
            "alt": "Gift"
        },
        {
            "src": "https://cdn-icons-png.flaticon.com/256/12792/12792049.png",
            "alt": "Gift"
        },
        {
            "src": "https://cdn-icons-png.flaticon.com/256/12792/12792053.png",
            "alt": "Gift"
        },
        {
            "src": "https://cdn-icons-png.flaticon.com/256/12792/12792057.png",
            "alt": "Gift"
        },
        {
            "src": "https://cdn-icons-png.flaticon.com/256/12792/12792061.png",
            "alt": "Gift"
        },
        {
            "src": "https://cdn-icons-png.flaticon.com/256/12792/12792065.png",
            "alt": "Gift"
        },
        {
            "src": "https://cdn-icons-png.flaticon.com/256/12792/12792069.png",
            "alt": "Gift"
        },
        {
            "src": "https://cdn-icons-png.flaticon.com/256/12792/12792073.png",
            "alt": "Gift"
        },
        {
            "src": "https://cdn-icons-png.flaticon.com/256/12792/12792078.png",
            "alt": "Gift"
        },
        {
            "src": "https://cdn-icons-png.flaticon.com/256/12792/12792081.png",
            "alt": "Gift"
        },
        {
            "src": "https://cdn-icons-png.flaticon.com/256/12792/12792083.png",
            "alt": "Gift"
        },
        {
            "src": "https://cdn-icons-png.flaticon.com/256/12792/12792085.png",
            "alt": "Gift"
        },
        {
            "src": "https://cdn-icons-png.flaticon.com/256/12792/12792087.png",
            "alt": "Gift"
        },
        {
            "src": "https://cdn-icons-png.flaticon.com/256/12792/12792089.png",
            "alt": "Gift"
        },
        {
            "src": "https://cdn-icons-png.flaticon.com/256/12792/12792091.png",
            "alt": "Gift"
        },
        {
            "src": "https://cdn-icons-png.flaticon.com/256/12792/12792093.png",
            "alt": "Gift"
        },
        {
            "src": "https://cdn-icons-png.flaticon.com/256/12792/12792095.png",
            "alt": "Gift"
        },
        {
            "src": "https://cdn-icons-png.flaticon.com/256/12971/12971562.png",
            "alt": "Gift"
        },
        {
            "src": "https://cdn-icons-png.flaticon.com/256/12971/12971563.png",
            "alt": "Gift"
        },
        {
            "src": "https://cdn-icons-png.flaticon.com/256/12971/12971564.png",
            "alt": "Wishlist"
        },
        {
            "src": "https://cdn-icons-png.flaticon.com/256/12971/12971565.png",
            "alt": "Diamond ring"
        },
        {
            "src": "https://cdn-icons-png.flaticon.com/256/12971/12971566.png",
            "alt": "Books"
        },
        {
            "src": "https://cdn-icons-png.flaticon.com/256/12971/12971567.png",
            "alt": "Surprise"
        },
        {
            "src": "https://cdn-icons-png.flaticon.com/256/12971/12971568.png",
            "alt": "Gift"
        },
        {
            "src": "https://cdn-icons-png.flaticon.com/256/12971/12971569.png",
            "alt": "Gift"
        },
        {
            "src": "https://cdn-icons-png.flaticon.com/256/12971/12971570.png",
            "alt": "Wish"
        },
        {
            "src": "https://cdn-icons-png.flaticon.com/256/12971/12971571.png",
            "alt": "Car"
        },
        {
            "src": "https://cdn-icons-png.flaticon.com/256/12971/12971572.png",
            "alt": "Gift"
        },
        {
            "src": "https://cdn-icons-png.flaticon.com/256/12971/12971573.png",
            "alt": "Gift"
        },
        {
            "src": "https://cdn-icons-png.flaticon.com/256/12971/12971574.png",
            "alt": "Gift"
        },
        {
            "src": "https://cdn-icons-png.flaticon.com/256/12971/12971575.png",
            "alt": "Flowers"
        },
        {
            "src": "https://cdn-icons-png.flaticon.com/256/12971/12971576.png",
            "alt": "Money"
        },
        {
            "src": "https://cdn-icons-png.flaticon.com/256/12971/12971577.png",
            "alt": "Gift"
        },
        {
            "src": "https://cdn-icons-png.flaticon.com/256/12971/12971578.png",
            "alt": "Gift"
        },
        {
            "src": "https://cdn-icons-png.flaticon.com/256/12971/12971579.png",
            "alt": "Gift"
        },
        {
            "src": "https://cdn-icons-png.flaticon.com/256/12971/12971580.png",
            "alt": "Voucher"
        },
        {
            "src": "https://cdn-icons-png.flaticon.com/256/12971/12971581.png",
            "alt": "Gift"
        },
        {
            "src": "https://cdn-icons-png.flaticon.com/256/13048/13048871.png",
            "alt": "Gifts"
        },
        {
            "src": "https://cdn-icons-png.flaticon.com/256/13048/13048881.png",
            "alt": "Gifts"
        },
        {
            "src": "https://cdn-icons-png.flaticon.com/256/13048/13048887.png",
            "alt": "Gifts"
        },
        {
            "src": "https://cdn-icons-png.flaticon.com/256/13048/13048893.png",
            "alt": "Gifts"
        },
        {
            "src": "https://cdn-icons-png.flaticon.com/256/13048/13048897.png",
            "alt": "Gifts"
        },
        {
            "src": "https://cdn-icons-png.flaticon.com/256/13048/13048903.png",
            "alt": "Gifts"
        },
        {
            "src": "https://cdn-icons-png.flaticon.com/256/13048/13048908.png",
            "alt": "Gifts"
        },
        {
            "src": "https://cdn-icons-png.flaticon.com/256/13048/13048913.png",
            "alt": "Gifts"
        },
        {
            "src": "https://cdn-icons-png.flaticon.com/256/13048/13048920.png",
            "alt": "Gifts"
        },
        {
            "src": "https://cdn-icons-png.flaticon.com/256/13048/13048925.png",
            "alt": "Gifts"
        },
        {
            "src": "https://cdn-icons-png.flaticon.com/256/13048/13048934.png",
            "alt": "Gifts"
        },
        {
            "src": "https://cdn-icons-png.flaticon.com/256/13048/13048941.png",
            "alt": "Gifts"
        },
        {
            "src": "https://cdn-icons-png.flaticon.com/256/13048/13048948.png",
            "alt": "Gifts"
        },
        {
            "src": "https://cdn-icons-png.flaticon.com/256/13048/13048954.png",
            "alt": "Gifts"
        },
        {
            "src": "https://cdn-icons-png.flaticon.com/256/13048/13048962.png",
            "alt": "Wedding ring"
        },
        {
            "src": "https://cdn-icons-png.flaticon.com/256/13048/13048969.png",
            "alt": "Gifts"
        },
        {
            "src": "https://cdn-icons-png.flaticon.com/256/13048/13048976.png",
            "alt": "Gifts"
        },
        {
            "src": "https://cdn-icons-png.flaticon.com/256/13048/13048982.png",
            "alt": "Gifts"
        },
        {
            "src": "https://cdn-icons-png.flaticon.com/256/13048/13048990.png",
            "alt": "Gifts"
        },
        {
            "src": "https://cdn-icons-png.flaticon.com/256/13048/13048997.png",
            "alt": "Gifts"
        },
        {
            "src": "https://cdn-icons-png.flaticon.com/256/13297/13297399.png",
            "alt": "Gift"
        },
        {
            "src": "https://cdn-icons-png.flaticon.com/256/13297/13297401.png",
            "alt": "Gift"
        },
        {
            "src": "https://cdn-icons-png.flaticon.com/256/13297/13297403.png",
            "alt": "Gift"
        },
        {
            "src": "https://cdn-icons-png.flaticon.com/256/13297/13297405.png",
            "alt": "Gift"
        },
        {
            "src": "https://cdn-icons-png.flaticon.com/256/13297/13297406.png",
            "alt": "Gift"
        },
        {
            "src": "https://cdn-icons-png.flaticon.com/256/13297/13297408.png",
            "alt": "Gift"
        },
        {
            "src": "https://cdn-icons-png.flaticon.com/256/13297/13297410.png",
            "alt": "Gift"
        },
        {
            "src": "https://cdn-icons-png.flaticon.com/256/13297/13297411.png",
            "alt": "Gift"
        },
        {
            "src": "https://cdn-icons-png.flaticon.com/256/13297/13297413.png",
            "alt": "Gift"
        },
        {
            "src": "https://cdn-icons-png.flaticon.com/256/13297/13297415.png",
            "alt": "Gift"
        },
        {
            "src": "https://cdn-icons-png.flaticon.com/256/13297/13297417.png",
            "alt": "Gift"
        },
        {
            "src": "https://cdn-icons-png.flaticon.com/256/13297/13297418.png",
            "alt": "Gift"
        },
        {
            "src": "https://cdn-icons-png.flaticon.com/256/13297/13297420.png",
            "alt": "Gift"
        },
        {
            "src": "https://cdn-icons-png.flaticon.com/256/13297/13297422.png",
            "alt": "Gift"
        },
        {
            "src": "https://cdn-icons-png.flaticon.com/256/13297/13297423.png",
            "alt": "Gift"
        },
        {
            "src": "https://cdn-icons-png.flaticon.com/256/13297/13297424.png",
            "alt": "Gift"
        },
        {
            "src": "https://cdn-icons-png.flaticon.com/256/13297/13297425.png",
            "alt": "Gift"
        },
        {
            "src": "https://cdn-icons-png.flaticon.com/256/13297/13297426.png",
            "alt": "Gift"
        },
        {
            "src": "https://cdn-icons-png.flaticon.com/256/13297/13297427.png",
            "alt": "Gift"
        },
        {
            "src": "https://cdn-icons-png.flaticon.com/256/13297/13297428.png",
            "alt": "Gift"
        }
    ]
}