{
    "package": "Healthy food",
    "imgList": [
        {
            "src": "https://cdn-icons-png.flaticon.com/256/8872/8872397.png",
            "alt": "Fruit Salad"
        },
        {
            "src": "https://cdn-icons-png.flaticon.com/256/8872/8872399.png",
            "alt": "Citric"
        },
        {
            "src": "https://cdn-icons-png.flaticon.com/256/8872/8872401.png",
            "alt": "Melon"
        },
        {
            "src": "https://cdn-icons-png.flaticon.com/256/8872/8872403.png",
            "alt": "Avocado"
        },
        {
            "src": "https://cdn-icons-png.flaticon.com/256/8872/8872405.png",
            "alt": "Fruit"
        },
        {
            "src": "https://cdn-icons-png.flaticon.com/256/8872/8872407.png",
            "alt": "Juice"
        },
        {
            "src": "https://cdn-icons-png.flaticon.com/256/8872/8872409.png",
            "alt": "Vegetables"
        },
        {
            "src": "https://cdn-icons-png.flaticon.com/256/8872/8872411.png",
            "alt": "Cauliflower"
        },
        {
            "src": "https://cdn-icons-png.flaticon.com/256/8872/8872413.png",
            "alt": "Milk"
        },
        {
            "src": "https://cdn-icons-png.flaticon.com/256/8872/8872415.png",
            "alt": "Food"
        },
        {
            "src": "https://cdn-icons-png.flaticon.com/256/8872/8872416.png",
            "alt": "Watermelon"
        },
        {
            "src": "https://cdn-icons-png.flaticon.com/256/8872/8872417.png",
            "alt": "Pomegranate"
        },
        {
            "src": "https://cdn-icons-png.flaticon.com/256/8872/8872418.png",
            "alt": "Fruit"
        },
        {
            "src": "https://cdn-icons-png.flaticon.com/256/8872/8872419.png",
            "alt": "Papaya"
        },
        {
            "src": "https://cdn-icons-png.flaticon.com/256/8872/8872420.png",
            "alt": "Honey"
        },
        {
            "src": "https://cdn-icons-png.flaticon.com/256/8872/8872421.png",
            "alt": "Juice"
        },
        {
            "src": "https://cdn-icons-png.flaticon.com/256/8872/8872422.png",
            "alt": "Healthy Food"
        },
        {
            "src": "https://cdn-icons-png.flaticon.com/256/8872/8872423.png",
            "alt": "Pumpkin"
        },
        {
            "src": "https://cdn-icons-png.flaticon.com/256/8872/8872424.png",
            "alt": "Mushroom"
        },
        {
            "src": "https://cdn-icons-png.flaticon.com/256/8872/8872425.png",
            "alt": "Yogurt"
        },
        {
            "src": "https://cdn-icons-png.flaticon.com/256/9496/9496789.png",
            "alt": "Healthy Food"
        },
        {
            "src": "https://cdn-icons-png.flaticon.com/256/9496/9496790.png",
            "alt": "Salad"
        },
        {
            "src": "https://cdn-icons-png.flaticon.com/256/9496/9496791.png",
            "alt": "Strawberry juice"
        },
        {
            "src": "https://cdn-icons-png.flaticon.com/256/9496/9496792.png",
            "alt": "Breakfast"
        },
        {
            "src": "https://cdn-icons-png.flaticon.com/256/9496/9496793.png",
            "alt": "Fruit juice"
        },
        {
            "src": "https://cdn-icons-png.flaticon.com/256/9496/9496794.png",
            "alt": "Healthy Food"
        },
        {
            "src": "https://cdn-icons-png.flaticon.com/256/9496/9496795.png",
            "alt": "Eating"
        },
        {
            "src": "https://cdn-icons-png.flaticon.com/256/9496/9496796.png",
            "alt": "Healthy Food"
        },
        {
            "src": "https://cdn-icons-png.flaticon.com/256/9496/9496797.png",
            "alt": "Avocado"
        },
        {
            "src": "https://cdn-icons-png.flaticon.com/256/9496/9496798.png",
            "alt": "Onion"
        },
        {
            "src": "https://cdn-icons-png.flaticon.com/256/9496/9496799.png",
            "alt": "Apple"
        },
        {
            "src": "https://cdn-icons-png.flaticon.com/256/9496/9496800.png",
            "alt": "Healthy Food"
        },
        {
            "src": "https://cdn-icons-png.flaticon.com/256/9496/9496801.png",
            "alt": "Healthy Food"
        },
        {
            "src": "https://cdn-icons-png.flaticon.com/256/9496/9496802.png",
            "alt": "Paper bag"
        },
        {
            "src": "https://cdn-icons-png.flaticon.com/256/9496/9496803.png",
            "alt": "Healthy Food"
        },
        {
            "src": "https://cdn-icons-png.flaticon.com/256/9496/9496804.png",
            "alt": "Veggies"
        },
        {
            "src": "https://cdn-icons-png.flaticon.com/256/9496/9496805.png",
            "alt": "Cutting"
        },
        {
            "src": "https://cdn-icons-png.flaticon.com/256/9496/9496806.png",
            "alt": "Salad"
        },
        {
            "src": "https://cdn-icons-png.flaticon.com/256/9496/9496807.png",
            "alt": "Salad"
        },
        {
            "src": "https://cdn-icons-png.flaticon.com/256/9496/9496808.png",
            "alt": "Healthy Food"
        },
        {
            "src": "https://cdn-icons-png.flaticon.com/256/9560/9560373.png",
            "alt": "Yogurt"
        },
        {
            "src": "https://cdn-icons-png.flaticon.com/256/9560/9560374.png",
            "alt": "Blender"
        },
        {
            "src": "https://cdn-icons-png.flaticon.com/256/9560/9560375.png",
            "alt": "Turnip"
        },
        {
            "src": "https://cdn-icons-png.flaticon.com/256/9560/9560376.png",
            "alt": "Carrot"
        },
        {
            "src": "https://cdn-icons-png.flaticon.com/256/9560/9560377.png",
            "alt": "Fruit"
        },
        {
            "src": "https://cdn-icons-png.flaticon.com/256/9560/9560378.png",
            "alt": "Oil"
        },
        {
            "src": "https://cdn-icons-png.flaticon.com/256/9560/9560379.png",
            "alt": "Artichoke"
        },
        {
            "src": "https://cdn-icons-png.flaticon.com/256/9560/9560380.png",
            "alt": "Broccoli"
        },
        {
            "src": "https://cdn-icons-png.flaticon.com/256/9560/9560381.png",
            "alt": "Honey"
        },
        {
            "src": "https://cdn-icons-png.flaticon.com/256/9560/9560382.png",
            "alt": "Orange Juice"
        },
        {
            "src": "https://cdn-icons-png.flaticon.com/256/9560/9560383.png",
            "alt": "Pineapple"
        },
        {
            "src": "https://cdn-icons-png.flaticon.com/256/9560/9560384.png",
            "alt": "Avocado"
        },
        {
            "src": "https://cdn-icons-png.flaticon.com/256/9560/9560385.png",
            "alt": "Apple"
        },
        {
            "src": "https://cdn-icons-png.flaticon.com/256/9560/9560386.png",
            "alt": "Dairy products"
        },
        {
            "src": "https://cdn-icons-png.flaticon.com/256/9560/9560387.png",
            "alt": "Onion"
        },
        {
            "src": "https://cdn-icons-png.flaticon.com/256/9560/9560388.png",
            "alt": "Apple"
        },
        {
            "src": "https://cdn-icons-png.flaticon.com/256/9560/9560389.png",
            "alt": "Salad"
        },
        {
            "src": "https://cdn-icons-png.flaticon.com/256/9560/9560390.png",
            "alt": "Eggs"
        },
        {
            "src": "https://cdn-icons-png.flaticon.com/256/9560/9560391.png",
            "alt": "Eggplant"
        },
        {
            "src": "https://cdn-icons-png.flaticon.com/256/9560/9560392.png",
            "alt": "Pear"
        },
        {
            "src": "https://cdn-icons-png.flaticon.com/256/9905/9905402.png",
            "alt": "Orange"
        },
        {
            "src": "https://cdn-icons-png.flaticon.com/256/9905/9905403.png",
            "alt": "Toast"
        },
        {
            "src": "https://cdn-icons-png.flaticon.com/256/9905/9905404.png",
            "alt": "Juice"
        },
        {
            "src": "https://cdn-icons-png.flaticon.com/256/9905/9905405.png",
            "alt": "Smoothie"
        },
        {
            "src": "https://cdn-icons-png.flaticon.com/256/9905/9905406.png",
            "alt": "Healthy Food"
        },
        {
            "src": "https://cdn-icons-png.flaticon.com/256/9905/9905407.png",
            "alt": "Healthy Food"
        },
        {
            "src": "https://cdn-icons-png.flaticon.com/256/9905/9905408.png",
            "alt": "Soup"
        },
        {
            "src": "https://cdn-icons-png.flaticon.com/256/9905/9905409.png",
            "alt": "Tomatoes"
        },
        {
            "src": "https://cdn-icons-png.flaticon.com/256/9905/9905410.png",
            "alt": "Fruit"
        },
        {
            "src": "https://cdn-icons-png.flaticon.com/256/9905/9905411.png",
            "alt": "Fruit"
        },
        {
            "src": "https://cdn-icons-png.flaticon.com/256/9905/9905412.png",
            "alt": "Salmon"
        },
        {
            "src": "https://cdn-icons-png.flaticon.com/256/9905/9905413.png",
            "alt": "Juice"
        },
        {
            "src": "https://cdn-icons-png.flaticon.com/256/9905/9905414.png",
            "alt": "Avocado"
        },
        {
            "src": "https://cdn-icons-png.flaticon.com/256/9905/9905415.png",
            "alt": "Quinoa"
        },
        {
            "src": "https://cdn-icons-png.flaticon.com/256/9905/9905416.png",
            "alt": "Fruit"
        },
        {
            "src": "https://cdn-icons-png.flaticon.com/256/9905/9905417.png",
            "alt": "Olive Oil"
        },
        {
            "src": "https://cdn-icons-png.flaticon.com/256/9905/9905418.png",
            "alt": "Egg"
        },
        {
            "src": "https://cdn-icons-png.flaticon.com/256/9905/9905419.png",
            "alt": "Fruit"
        },
        {
            "src": "https://cdn-icons-png.flaticon.com/256/9905/9905420.png",
            "alt": "Healthy Food"
        },
        {
            "src": "https://cdn-icons-png.flaticon.com/256/9905/9905421.png",
            "alt": "Oatmeal"
        },
        {
            "src": "https://cdn-icons-png.flaticon.com/256/10521/10521912.png",
            "alt": "Healthy food"
        },
        {
            "src": "https://cdn-icons-png.flaticon.com/256/10521/10521916.png",
            "alt": "Healthy food"
        },
        {
            "src": "https://cdn-icons-png.flaticon.com/256/10521/10521920.png",
            "alt": "Healthy food"
        },
        {
            "src": "https://cdn-icons-png.flaticon.com/256/10521/10521924.png",
            "alt": "Healthy food"
        },
        {
            "src": "https://cdn-icons-png.flaticon.com/256/10521/10521927.png",
            "alt": "Healthy food"
        },
        {
            "src": "https://cdn-icons-png.flaticon.com/256/10521/10521929.png",
            "alt": "Healthy food"
        },
        {
            "src": "https://cdn-icons-png.flaticon.com/256/10521/10521931.png",
            "alt": "Healthy food"
        },
        {
            "src": "https://cdn-icons-png.flaticon.com/256/10521/10521933.png",
            "alt": "Healthy food"
        },
        {
            "src": "https://cdn-icons-png.flaticon.com/256/10521/10521935.png",
            "alt": "Healthy food"
        },
        {
            "src": "https://cdn-icons-png.flaticon.com/256/10521/10521937.png",
            "alt": "Healthy food"
        },
        {
            "src": "https://cdn-icons-png.flaticon.com/256/10521/10521938.png",
            "alt": "Healthy food"
        },
        {
            "src": "https://cdn-icons-png.flaticon.com/256/10521/10521939.png",
            "alt": "Healthy food"
        },
        {
            "src": "https://cdn-icons-png.flaticon.com/256/10521/10521940.png",
            "alt": "Healthy food"
        },
        {
            "src": "https://cdn-icons-png.flaticon.com/256/10521/10521941.png",
            "alt": "Healthy food"
        },
        {
            "src": "https://cdn-icons-png.flaticon.com/256/10521/10521942.png",
            "alt": "Healthy food"
        },
        {
            "src": "https://cdn-icons-png.flaticon.com/256/10521/10521943.png",
            "alt": "Healthy food"
        },
        {
            "src": "https://cdn-icons-png.flaticon.com/256/10521/10521944.png",
            "alt": "Healthy food"
        },
        {
            "src": "https://cdn-icons-png.flaticon.com/256/10521/10521945.png",
            "alt": "Healthy food"
        },
        {
            "src": "https://cdn-icons-png.flaticon.com/256/10521/10521946.png",
            "alt": "Healthy food"
        },
        {
            "src": "https://cdn-icons-png.flaticon.com/256/10521/10521947.png",
            "alt": "Healthy food"
        },
        {
            "src": "https://cdn-icons-png.flaticon.com/256/11200/11200841.png",
            "alt": "Avocado"
        },
        {
            "src": "https://cdn-icons-png.flaticon.com/256/11200/11200843.png",
            "alt": "Salad"
        },
        {
            "src": "https://cdn-icons-png.flaticon.com/256/11200/11200847.png",
            "alt": "Juice"
        },
        {
            "src": "https://cdn-icons-png.flaticon.com/256/11200/11200852.png",
            "alt": "Carrot"
        },
        {
            "src": "https://cdn-icons-png.flaticon.com/256/11200/11200855.png",
            "alt": "Infusion"
        },
        {
            "src": "https://cdn-icons-png.flaticon.com/256/11200/11200863.png",
            "alt": "Cutting"
        },
        {
            "src": "https://cdn-icons-png.flaticon.com/256/11200/11200868.png",
            "alt": "Smoothie"
        },
        {
            "src": "https://cdn-icons-png.flaticon.com/256/11200/11200877.png",
            "alt": "Spinach"
        },
        {
            "src": "https://cdn-icons-png.flaticon.com/256/11200/11200884.png",
            "alt": "Broccoli"
        },
        {
            "src": "https://cdn-icons-png.flaticon.com/256/11200/11200886.png",
            "alt": "Biscuit"
        },
        {
            "src": "https://cdn-icons-png.flaticon.com/256/11200/11200896.png",
            "alt": "Rice"
        },
        {
            "src": "https://cdn-icons-png.flaticon.com/256/11200/11200902.png",
            "alt": "Pouring"
        },
        {
            "src": "https://cdn-icons-png.flaticon.com/256/11200/11200904.png",
            "alt": "Water"
        },
        {
            "src": "https://cdn-icons-png.flaticon.com/256/11200/11200914.png",
            "alt": "Smoothie"
        },
        {
            "src": "https://cdn-icons-png.flaticon.com/256/11200/11200918.png",
            "alt": "Fruit bowl"
        },
        {
            "src": "https://cdn-icons-png.flaticon.com/256/11200/11200925.png",
            "alt": "Broccoli"
        },
        {
            "src": "https://cdn-icons-png.flaticon.com/256/11200/11200934.png",
            "alt": "Mixer"
        },
        {
            "src": "https://cdn-icons-png.flaticon.com/256/11200/11200935.png",
            "alt": "Plate"
        },
        {
            "src": "https://cdn-icons-png.flaticon.com/256/11200/11200942.png",
            "alt": "Basket"
        },
        {
            "src": "https://cdn-icons-png.flaticon.com/256/11200/11200947.png",
            "alt": "Apple"
        },
        {
            "src": "https://cdn-icons-png.flaticon.com/256/15093/15093422.png",
            "alt": "Apple"
        },
        {
            "src": "https://cdn-icons-png.flaticon.com/256/15093/15093423.png",
            "alt": "Almond milk"
        },
        {
            "src": "https://cdn-icons-png.flaticon.com/256/15093/15093424.png",
            "alt": "Meat"
        },
        {
            "src": "https://cdn-icons-png.flaticon.com/256/15093/15093425.png",
            "alt": "Dried fruits"
        },
        {
            "src": "https://cdn-icons-png.flaticon.com/256/15093/15093426.png",
            "alt": "Blender"
        },
        {
            "src": "https://cdn-icons-png.flaticon.com/256/15093/15093427.png",
            "alt": "Ginger"
        },
        {
            "src": "https://cdn-icons-png.flaticon.com/256/15093/15093428.png",
            "alt": "Salad"
        },
        {
            "src": "https://cdn-icons-png.flaticon.com/256/15093/15093429.png",
            "alt": "Eating"
        },
        {
            "src": "https://cdn-icons-png.flaticon.com/256/15093/15093430.png",
            "alt": "Asparagus"
        },
        {
            "src": "https://cdn-icons-png.flaticon.com/256/15093/15093431.png",
            "alt": "Tofu"
        },
        {
            "src": "https://cdn-icons-png.flaticon.com/256/15093/15093432.png",
            "alt": "Peanut butter"
        },
        {
            "src": "https://cdn-icons-png.flaticon.com/256/15093/15093433.png",
            "alt": "Carrot"
        },
        {
            "src": "https://cdn-icons-png.flaticon.com/256/15093/15093434.png",
            "alt": "Honey"
        },
        {
            "src": "https://cdn-icons-png.flaticon.com/256/15093/15093435.png",
            "alt": "Egg"
        },
        {
            "src": "https://cdn-icons-png.flaticon.com/256/15093/15093436.png",
            "alt": "Cucumber"
        },
        {
            "src": "https://cdn-icons-png.flaticon.com/256/15093/15093437.png",
            "alt": "Healthy food"
        },
        {
            "src": "https://cdn-icons-png.flaticon.com/256/15093/15093438.png",
            "alt": "Avocado"
        },
        {
            "src": "https://cdn-icons-png.flaticon.com/256/15093/15093439.png",
            "alt": "Steamed food"
        },
        {
            "src": "https://cdn-icons-png.flaticon.com/256/15093/15093440.png",
            "alt": "Salad"
        },
        {
            "src": "https://cdn-icons-png.flaticon.com/256/15093/15093441.png",
            "alt": "Drink"
        }
    ]
}