{
    "package": "Motivational",
    "imgList": [
        {
            "src": "https://cdn-icons-png.flaticon.com/256/7591/7591561.png",
            "alt": "Good idea"
        },
        {
            "src": "https://cdn-icons-png.flaticon.com/256/7591/7591563.png",
            "alt": "Airplane"
        },
        {
            "src": "https://cdn-icons-png.flaticon.com/256/7591/7591565.png",
            "alt": "Give up"
        },
        {
            "src": "https://cdn-icons-png.flaticon.com/256/7591/7591567.png",
            "alt": "Awesome"
        },
        {
            "src": "https://cdn-icons-png.flaticon.com/256/7591/7591569.png",
            "alt": "Medal"
        },
        {
            "src": "https://cdn-icons-png.flaticon.com/256/7591/7591571.png",
            "alt": "Rainbow"
        },
        {
            "src": "https://cdn-icons-png.flaticon.com/256/7591/7591573.png",
            "alt": "Unicorn"
        },
        {
            "src": "https://cdn-icons-png.flaticon.com/256/7591/7591575.png",
            "alt": "Archery"
        },
        {
            "src": "https://cdn-icons-png.flaticon.com/256/7591/7591576.png",
            "alt": "Star"
        },
        {
            "src": "https://cdn-icons-png.flaticon.com/256/7591/7591578.png",
            "alt": "Well done"
        },
        {
            "src": "https://cdn-icons-png.flaticon.com/256/7591/7591580.png",
            "alt": "Emoji"
        },
        {
            "src": "https://cdn-icons-png.flaticon.com/256/7591/7591582.png",
            "alt": "Rise"
        },
        {
            "src": "https://cdn-icons-png.flaticon.com/256/7591/7591584.png",
            "alt": "Girl power"
        },
        {
            "src": "https://cdn-icons-png.flaticon.com/256/7591/7591586.png",
            "alt": "Star"
        },
        {
            "src": "https://cdn-icons-png.flaticon.com/256/7591/7591589.png",
            "alt": "Lets go"
        },
        {
            "src": "https://cdn-icons-png.flaticon.com/256/7591/7591593.png",
            "alt": "Proud"
        },
        {
            "src": "https://cdn-icons-png.flaticon.com/256/7591/7591595.png",
            "alt": "Love yourself"
        },
        {
            "src": "https://cdn-icons-png.flaticon.com/256/7591/7591598.png",
            "alt": "Star"
        },
        {
            "src": "https://cdn-icons-png.flaticon.com/256/7591/7591600.png",
            "alt": "Smiling"
        },
        {
            "src": "https://cdn-icons-png.flaticon.com/256/7591/7591605.png",
            "alt": "Good"
        },
        {
            "src": "https://cdn-icons-png.flaticon.com/256/7591/7591607.png",
            "alt": "Great"
        },
        {
            "src": "https://cdn-icons-png.flaticon.com/256/7591/7591609.png",
            "alt": "Shine"
        },
        {
            "src": "https://cdn-icons-png.flaticon.com/256/7591/7591612.png",
            "alt": "Grow"
        },
        {
            "src": "https://cdn-icons-png.flaticon.com/256/7591/7591615.png",
            "alt": "Heal"
        },
        {
            "src": "https://cdn-icons-png.flaticon.com/256/7591/7591620.png",
            "alt": "Great job"
        },
        {
            "src": "https://cdn-icons-png.flaticon.com/256/7591/7591622.png",
            "alt": "Cool"
        },
        {
            "src": "https://cdn-icons-png.flaticon.com/256/7591/7591625.png",
            "alt": "Egg"
        },
        {
            "src": "https://cdn-icons-png.flaticon.com/256/7591/7591629.png",
            "alt": "Good job"
        },
        {
            "src": "https://cdn-icons-png.flaticon.com/256/7591/7591633.png",
            "alt": "Nice"
        },
        {
            "src": "https://cdn-icons-png.flaticon.com/256/7591/7591639.png",
            "alt": "Wow"
        },
        {
            "src": "https://cdn-icons-png.flaticon.com/256/8776/8776391.png",
            "alt": "Sun"
        },
        {
            "src": "https://cdn-icons-png.flaticon.com/256/8776/8776396.png",
            "alt": "Magic"
        },
        {
            "src": "https://cdn-icons-png.flaticon.com/256/8776/8776399.png",
            "alt": "Unicorn"
        },
        {
            "src": "https://cdn-icons-png.flaticon.com/256/8776/8776402.png",
            "alt": "Bat animal"
        },
        {
            "src": "https://cdn-icons-png.flaticon.com/256/8776/8776406.png",
            "alt": "Perfume"
        },
        {
            "src": "https://cdn-icons-png.flaticon.com/256/8776/8776408.png",
            "alt": "Coffee mug"
        },
        {
            "src": "https://cdn-icons-png.flaticon.com/256/8776/8776410.png",
            "alt": "Love"
        },
        {
            "src": "https://cdn-icons-png.flaticon.com/256/8776/8776412.png",
            "alt": "Thumb up"
        },
        {
            "src": "https://cdn-icons-png.flaticon.com/256/8776/8776414.png",
            "alt": "Ice cream"
        },
        {
            "src": "https://cdn-icons-png.flaticon.com/256/8776/8776416.png",
            "alt": "Suitcase"
        },
        {
            "src": "https://cdn-icons-png.flaticon.com/256/8776/8776418.png",
            "alt": "Earth"
        },
        {
            "src": "https://cdn-icons-png.flaticon.com/256/8776/8776420.png",
            "alt": "Flower Pot"
        },
        {
            "src": "https://cdn-icons-png.flaticon.com/256/8776/8776422.png",
            "alt": "Love"
        },
        {
            "src": "https://cdn-icons-png.flaticon.com/256/8776/8776424.png",
            "alt": "Radio"
        },
        {
            "src": "https://cdn-icons-png.flaticon.com/256/8776/8776426.png",
            "alt": "Archery"
        },
        {
            "src": "https://cdn-icons-png.flaticon.com/256/8776/8776428.png",
            "alt": "Wing"
        },
        {
            "src": "https://cdn-icons-png.flaticon.com/256/8776/8776430.png",
            "alt": "Wrist Watch"
        },
        {
            "src": "https://cdn-icons-png.flaticon.com/256/8776/8776432.png",
            "alt": "Eye"
        },
        {
            "src": "https://cdn-icons-png.flaticon.com/256/8776/8776435.png",
            "alt": "Face"
        },
        {
            "src": "https://cdn-icons-png.flaticon.com/256/8776/8776437.png",
            "alt": "Best"
        },
        {
            "src": "https://cdn-icons-png.flaticon.com/256/8776/8776439.png",
            "alt": "Stopwatch"
        },
        {
            "src": "https://cdn-icons-png.flaticon.com/256/8776/8776441.png",
            "alt": "Winner"
        },
        {
            "src": "https://cdn-icons-png.flaticon.com/256/8776/8776443.png",
            "alt": "Wall clock"
        },
        {
            "src": "https://cdn-icons-png.flaticon.com/256/8776/8776445.png",
            "alt": "Badge"
        },
        {
            "src": "https://cdn-icons-png.flaticon.com/256/8776/8776447.png",
            "alt": "Star"
        },
        {
            "src": "https://cdn-icons-png.flaticon.com/256/8776/8776448.png",
            "alt": "Cloud"
        },
        {
            "src": "https://cdn-icons-png.flaticon.com/256/8776/8776449.png",
            "alt": "Star"
        },
        {
            "src": "https://cdn-icons-png.flaticon.com/256/8776/8776450.png",
            "alt": "Document"
        },
        {
            "src": "https://cdn-icons-png.flaticon.com/256/8776/8776451.png",
            "alt": "Badge"
        },
        {
            "src": "https://cdn-icons-png.flaticon.com/256/8776/8776452.png",
            "alt": "Light bulb"
        },
        {
            "src": "https://cdn-icons-png.flaticon.com/256/8776/8776453.png",
            "alt": "Rocket"
        },
        {
            "src": "https://cdn-icons-png.flaticon.com/256/8776/8776454.png",
            "alt": "Speech bubble"
        },
        {
            "src": "https://cdn-icons-png.flaticon.com/256/8776/8776455.png",
            "alt": "Diamond"
        },
        {
            "src": "https://cdn-icons-png.flaticon.com/256/8776/8776456.png",
            "alt": "Heart"
        },
        {
            "src": "https://cdn-icons-png.flaticon.com/256/8776/8776457.png",
            "alt": "Book"
        },
        {
            "src": "https://cdn-icons-png.flaticon.com/256/8776/8776458.png",
            "alt": "Lips"
        },
        {
            "src": "https://cdn-icons-png.flaticon.com/256/8776/8776459.png",
            "alt": "Star"
        },
        {
            "src": "https://cdn-icons-png.flaticon.com/256/8776/8776460.png",
            "alt": "Eye mask"
        },
        {
            "src": "https://cdn-icons-png.flaticon.com/256/8776/8776461.png",
            "alt": "Rainbow"
        },
        {
            "src": "https://cdn-icons-png.flaticon.com/256/8776/8776462.png",
            "alt": "Shoe"
        }
    ]
}